pbi_local_connector/__init__.py
pbi_local_connector/main.py
pbi_local_connector/test.py
pbi_local_connector-0.5.dist-info/METADATA
pbi_local_connector-0.5.dist-info/WHEEL
pbi_local_connector-0.5.dist-info/top_level.txt
pbi_local_connector-0.5.dist-info/RECORD
