Metadata-Version: 2.1
Name: pbi_local_connector
Version: 0.5
Summary: Provides utilities to read data from PowerBI dataset open locally
Home-page: https://github.com/Alexandre-RM/pbi_local_connector
Author: ARM
Requires-Dist: pandas
Requires-Dist: pyadomd
